<annotation verified="no">
  <folder>JPEGImages</folder>
  <filename>000369</filename>
  <path>C:\Users\Lyw\Desktop\yue\JPEGImages\000369.jpg</path>
  <source>
    <database>Unknown</database>
  </source>
  <size>
    <width>800</width>
    <height>450</height>
    <depth>3</depth>
  </size>
  <segmented>0</segmented>
  <object>
    <name>swimmers</name>
    <pose>Unspecified</pose>
    <truncated>0</truncated>
    <Difficult>0</Difficult>
    <bndbox>
      <xmin>238</xmin>
      <ymin>237</ymin>
      <xmax>293</xmax>
      <ymax>261</ymax>
    </bndbox>
  </object>
  <object>
    <name>swimmers</name>
    <pose>Unspecified</pose>
    <truncated>0</truncated>
    <Difficult>0</Difficult>
    <bndbox>
      <xmin>344</xmin>
      <ymin>198</ymin>
      <xmax>400</xmax>
      <ymax>227</ymax>
    </bndbox>
  </object>
</annotation>
