<annotation verified="no">
  <folder>JPEGImages</folder>
  <filename>000860</filename>
  <path>C:\Users\Administrator\Desktop\hui\JPEGImages\000860.jpg</path>
  <source>
    <database>Unknown</database>
  </source>
  <size>
    <width>800</width>
    <height>450</height>
    <depth>3</depth>
  </size>
  <segmented>0</segmented>
  <object>
    <name>passerby</name>
    <pose>Unspecified</pose>
    <truncated>0</truncated>
    <Difficult>0</Difficult>
    <bndbox>
      <xmin>457</xmin>
      <ymin>273</ymin>
      <xmax>488</xmax>
      <ymax>377</ymax>
    </bndbox>
  </object>
</annotation>
