<annotation verified="no">
  <folder>JPEGImages</folder>
  <filename>001806</filename>
  <path>C:\Users\lenovo\Desktop\he\JPEGImages\001806.jpg</path>
  <source>
    <database>Unknown</database>
  </source>
  <size>
    <width>800</width>
    <height>450</height>
    <depth>3</depth>
  </size>
  <segmented>0</segmented>
  <object>
    <name>swimmers</name>
    <pose>Unspecified</pose>
    <truncated>0</truncated>
    <Difficult>0</Difficult>
    <bndbox>
      <xmin>285</xmin>
      <ymin>348</ymin>
      <xmax>360</xmax>
      <ymax>425</ymax>
    </bndbox>
  </object>
</annotation>
