<annotation verified="yes">
  <folder>JPEGImages</folder>
  <filename>001846</filename>
  <path>C:\Users\Administrator\Desktop\he\he\JPEGImages\001846.jpg</path>
  <source>
    <database>Unknown</database>
  </source>
  <size>
    <width>800</width>
    <height>450</height>
    <depth>3</depth>
  </size>
  <segmented>0</segmented>
  <object>
    <name>swimmers</name>
    <pose>Unspecified</pose>
    <truncated>0</truncated>
    <Difficult>0</Difficult>
    <bndbox>
      <xmin>235</xmin>
      <ymin>333</ymin>
      <xmax>292</xmax>
      <ymax>382</ymax>
    </bndbox>
  </object>
</annotation>
